{
  "status": "1",
  "data": [
      {
        "id": "1",        
        "facebook_interstial_splash_fail":"610009253562165_610009340228823",
        "facebook_interstial_fail":"610009253562165_610009333562157",
        "facebook_native_fail":"610009253562165_610009330228824",
        "facebook_banner":"610009253562165_610009343562156",
        "facebook_banner_fail":"610009253562165_706999793863110",
        "facebook_native_banner_fail":"610009253562165_707000083863081",
        "google_rewarded_ad": "/21753324030,22682963512/com.faceappfaceswap.com_Rewarded",
        "google_open_ads": "/21753324030,22682963512/com.faceappfaceswap.com_AppOpen",
        "google_banner": "/21753324030,22682963512/com.faceappfaceswap.com_Banner",
        "google_banner_fail": "/21753324030,22682963512/com.faceappfaceswap.com_Banner",
        "google_interstial_fail": "/21753324030,22682963512/com.faceappfaceswap.com_Interstitial",
        "google_interstial_splash_fail ": "/21753324030,22682963512/com.faceappfaceswap.com_Interstitial",
        "google_native_fail": "/21753324030,22682963512/com.faceappfaceswap.com_Native",
        "facebook_native_banner": "610009253562165_610009326895491",
        "common_native_banner": ["610009253562165_706997740529982","610009253562165_706997733863316","610009253562165_706997727196650","610009253562165_706997737196649","610009253562165_706997730529983"],
        "common_native": ["610009253562165_706996753863414","610009253562165_706996757196747","610009253562165_706996743863415","610009253562165_706996760530080"],
        "common_interstial": ["610009253562165_706987087197714","610009253562165_706989797197443","610009253562165_706987610530995","610009253562165_706987093864380","610009253562165_706987107197712","610009253562165_706987100531046","610009253562165_706987097197713","610009253562165_706987260531030","610009253562165_706987263864363","610009253562165_706987253864364","610009253562165_706987257197697","610009253562165_706987603864329","610009253562165_706987607197662","610009253562165_706987600530996"],
        "common_interstial_splash": ["/21753324030,22682963512/com.faceappfaceswap.com_Interstitial"],
        "moreapp_json": "https://raw.githubusercontent.com/mobapptechnology/mobapptechno_git/master/moreappdata_json.json",
        "moreapp_json_new": "https://raw.githubusercontent.com/mobapptechnology/mobapptechno_git/master/moreappdata_array.json",
        "app_title": "Face Swap",
        "interstitial_skip": 0,
        "adCountInCategory": 3,
        "native_priority": ["facebook"],
        "banner_priority": "3",
        "interstitial_priority": ["facebook"],
        "spalsh_interstitial_priority": ["google"],
        "fail_priority": "google",
        "openapp_fail": "facebook",
        "isActivitySkip": "y",
        "ad_interval_time": "0",
        "isSubcategory_active": "y",
        "app_redirectOtherAppStatus": "n",
        "webview_custom_tab": "n",
        "faceSwapLimit": 0,
        "img_upload_api": "http://178.62.25.207:8585/upload",
        "img_check_api": "http://178.62.25.207:8585/check",
        "face_swap_upload_api":"https://access1.imglarger.com/PhoAi/Upload",
        "face_swap_check_api":"https://access1.imglarger.com/PhoAi/CheckStatus",
        "isPhotoApiEnable":"n"
        
        
      }
  ]
}
