{
  "status": "1",
  "data": [
      {
        "id": "39",        
        "facebook_interstial_splash_fail":"54656546",
        "facebook_interstial_fail":"456546",
        "facebook_native_fail":"456456",
        "facebook_banner":"54654654",
        "facebook_banner_fail":"4656546",
        "facebook_native_banner_fail":"456456",
        "google_rewarded_ad": "546456546",
        "google_open_ads": "34556546",
        "google_banner": "45654654",
        "google_banner_fail": "54656546546",
        "google_interstial_fail": "",
        "google_interstial_splash_fail ": "",
        "google_native_fail": "",
        "common_native_bannersss": [""],
        "common_nativesss": [""],
        "common_interstial": [""],
        "common_interstial_splash": ["56546546546"],        
        "moreapp_json_new": "https://raw.githubusercontent.com/mobapptechnology/mobapptechno_gits/master/moreappdata_array.json",
        "app_title": "test1234567",
        "interstitial_skip": 0,
        "adCountInCategory": 0.5,
        "native_priority": ["googlexcvcxvcx"],
        "banner_priority": "0.5",
        "interstitial_priority": ["googlexcvxcv"],
        "spalsh_interstitial_priority": ["google"],
        "fail_priority": "googlesadsad",
        "openapp_fail": "facebooksadsad",
        "isActivitySkip": "y",
        "ad_interval_time": "0.5",
        "isSubcategory_active": "y",
        "app_redirectOtherAppStatus": "n",
        "webview_custom_tab": "n",
        "is_interstitial_at_call": "y",
        "trackplex_token": ["YkEZyciKEeynZ0IcvqllRQsdsadsad"],
        "isYoutubeEnable": "n",        
        "is_provider_enable": "y"
      }
  ]
}
